LICENSE
README.md
setup.py
test/__init__.py
test/test_cases.py
test/test_clustering.py
work_set_clustering/__init__.py
work_set_clustering/clustering.py
work_set_clustering/descriptive_key_utils.py
work_set_clustering/get_descriptive_keys_from_csv.py
work_set_clustering/get_descriptive_keys_from_xml.py
work_set_clustering/lib.py
work_set_clustering.egg-info/PKG-INFO
work_set_clustering.egg-info/SOURCES.txt
work_set_clustering.egg-info/dependency_links.txt
work_set_clustering.egg-info/top_level.txt