Metadata-Version: 2.1
Name: work-set-clustering
Version: 0.4.1
Summary: A Python script to perform a clustering based on descriptive keys.
Home-page: https://github.com/kbrbe/work-set-clustering
Author: Sven Lieber
Author-email: Sven.Lieber@kbr.be
License: AGPL-3.0
Keywords: FRBRization FRBR work-set-clustering
License-File: LICENSE
